fk_queue/__init__.py
fk_queue/config.py
fk_queue/audit/__init__.py
fk_queue/audit/audit.py
fk_queue/audit/bitacora.py
fk_queue/audit/logs.py
fk_queue/aws/__init__.py
fk_queue/aws/sqs.py
fk_queue/communicator/__init__.py
fk_queue/communicator/email.py
fk_queue/communicator/slack.py
fk_queue/communicator/sms.py
fk_queue-0.1.7836882855.dist-info/METADATA
fk_queue-0.1.7836882855.dist-info/WHEEL
fk_queue-0.1.7836882855.dist-info/top_level.txt
fk_queue-0.1.7836882855.dist-info/RECORD
