Metadata-Version: 2.1
Name: fk_queue
Version: 0.1.7836882855
Home-page: https://gitlab.com/f3315/team-back-end/cross/packages/package_queue
Author: Steven Santacruz Garcia
Author-email: stevengarcia1118@gmail.com
License: MIT
Requires-Dist: boto3
